License
pyproject.toml
setup.cfg
logntime/__init__.py
logntime.validation.assert.egg-info/PKG-INFO
logntime.validation.assert.egg-info/SOURCES.txt
logntime.validation.assert.egg-info/dependency_links.txt
logntime.validation.assert.egg-info/namespace_packages.txt
logntime.validation.assert.egg-info/top_level.txt
logntime/validation/__init__.py
logntime/validation/assertions/__init__.py
logntime/validation/assertions/assert_equals.py
logntime/validation/assertions/assert_exception.py
logntime/validation/assertions/assert_sequence_similarities.py
logntime/validation/assertions/assert_similarities.py
logntime/validation/assertions/compare.py
logntime/validation/assertions/transform.py